pkrhistoryparser/__init__.py
pkrhistoryparser/settings.py
pkrhistoryparser/history_parsers/__init__.py
pkrhistoryparser/history_parsers/abstract.py
pkrhistoryparser/history_parsers/cloud.py
pkrhistoryparser/history_parsers/local.py
pkrhistoryparser/lambda/__init__.py
pkrhistoryparser/lambda/history_parser.py
pkrhistoryparser/lambda/summary_parser.py
pkrhistoryparser/patterns/__init__.py
pkrhistoryparser/patterns/winamax.py
pkrhistoryparser/runs/__init__.py
pkrhistoryparser/runs/cloud/__init__.py
pkrhistoryparser/runs/cloud/correct_files.py
pkrhistoryparser/runs/cloud/parse_hand_histories.py
pkrhistoryparser/runs/cloud/parse_new_hand_histories.py
pkrhistoryparser/runs/cloud/parse_new_summaries.py
pkrhistoryparser/runs/cloud/parse_summaries.py
pkrhistoryparser/runs/local/__init__.py
pkrhistoryparser/runs/local/correct_files.py
pkrhistoryparser/runs/local/parse_hand_histories.py
pkrhistoryparser/runs/local/parse_new_hand_histories.py
pkrhistoryparser/runs/local/parse_new_summaries.py
pkrhistoryparser/runs/local/parse_summaries.py
pkrhistoryparser/summary_parsers/__init__.py
pkrhistoryparser/summary_parsers/abstract.py
pkrhistoryparser/summary_parsers/cloud.py
pkrhistoryparser/summary_parsers/local.py
pkrhistoryparser-3.0.4.dist-info/LICENSE.txt
pkrhistoryparser-3.0.4.dist-info/METADATA
pkrhistoryparser-3.0.4.dist-info/WHEEL
pkrhistoryparser-3.0.4.dist-info/top_level.txt
pkrhistoryparser-3.0.4.dist-info/RECORD
