Metadata-Version: 2.1
Name: pkrhistoryparser
Version: 3.0.4
Summary: A poker package to parse Hand histories into json objects
Home-page: https://github.com/manggy94/PokerHistoryParser
Author: Alexandre MANGWA
Author-email: alex.mangwa@gmail.com
License: MIT
Project-URL: Bug Tracker, https://github.com/manggy94/PokerHistoryParser/issues
Project-URL: Documentation, https://pkrhistoryparser.readthedocs.io/en/latest/parser/
Platform: UNKNOWN
Classifier: Development Status :: 4 - Beta
Classifier: Intended Audience :: Developers
Classifier: License :: OSI Approved :: MIT License
Classifier: Natural Language :: English
Classifier: Programming Language :: Python
Classifier: Programming Language :: Python :: 3
Classifier: Topic :: Games/Entertainment
Classifier: Topic :: Games/Entertainment :: Board Games
Requires-Python: >=3.10
License-File: LICENSE.txt
Requires-Dist: python-dotenv
